{"rowid":"1155","url":"https://mettl.com/en/english-proficiency-test-software/","http":200,"status":"ok","method":"extractor","title":"SpeechX: English proficiency test for communication skills evaluation","wordCount":1468,"text":"Trusted By Logo\n\nTrusted By Logo\n\nTrusted By Logo\n\nTrusted By Logo\n\nTrusted By Logo\n\nTrusted By Logo\n\nTrusted By Logo\n\nTrusted By Logo\n\nTrusted By Logo\n\nTrusted By Logo\n\nTrusted By Logo\n\nTrusted By Logo\n\nTrusted By Logo\n\nTrusted By Logo\n\nTrusted By Logo\n\nTrusted By Logo\n\nTrusted By Logo\n\nTrusted By Logo\n\n## English language assessment to evaluate and identify strong communicators\n\nSpeechX leverages Carnegie Speech, a patented speech recognition technology developed by Carnegie Mellon University, to deliver an AI-powered English-speaking test that is highly accurate and scalable.\n\nSpeechX measures four critical communication components:\n\n![]()\n\n### Pronunciation\n\nAssess candidates for critical, non-trainable pronunciation mistakes.\n\n### Fluency\n\nEvaluate candidates for 10+ dimensions like speaking rate, intonation, etc.\n\n### Grammar\n\nAssess candidates for critical, non-trainable grammatical errors.\n\n### Listening comprehension\n\nEvaluate candidates for fact and inference-based understanding.\n\n## Go beyond basic English tests for employees\n\nScientific speech evaluation benchmarked against global standards\n\n### Aligned to CEFR guidelines\n\nSpeechX evaluates candidates based on the Common European Framework of Reference (CEFR), which ensures consistency in assessing spoken English proficiency.\n\n### Culturally adaptive evaluation engine\n\nThe English proficiency test adjusts for native language influences, geographic dialects, and cultural nuances, offering unbiased assessments without penalizing diversity.\n\n### In-built cheating prevention stack\n\nFrom impersonation detection to secure browser compatibility, SpeechX includes a robust anti-cheating layer to maintain test integrity and authenticity.\n\n### Auto-graded results with actionable insights\n\nReceive instant, detailed reports with performance breakdowns and improvement areas, enabling smarter hiring and personalized training.\n\n## Move beyond spoken English to a holistic language evaluation\n\nLeverage our communication skills suite to find suitable candidates\n\n![]()\n\n### Spoken English skills\n\nEvaluate the proficiency to speak clearly, accurately, and logically\n\n![]()\n\n### Listening skills\n\nEvaluate the capability to listen and comprehend what others are communicating\n\n![]()\n\n### Reading skills\n\nEvaluate the ability to read, process, and retain written information\n\n![]()\n\n### Writing skills\n\nEvaluate the knowledge to express ideas and thoughts effectively through writing\n\n[](/en/communication-skills-assessment/)\n\n* * *\n\n## Use SpeechX to hire and develop talent effortlessly\n\nLeverage our English language proficiency test to meet organizational goals\n\n![]()\n\n### Campus hiring\n\nEfficiently evaluate and filter thousands of candidates at scale based on their communication skills with our spoken English test.\n\n![]()\n\n### Lateral hiring\n\nTransition to objective assessments and recruit individuals with outstanding communication skills for customer-facing and other pivotal roles.\n\n![]()\n\n### Training needs assessment\n\nAssess your workforce's communication abilities and help them develop tailored plans.\n\n## Assess communication skills for customer-facing roles\n\nSpeechX powers communication assessments across diverse sectors\n\n![]()\n\nIcon\n\n### BPO and customer support\n\nScreen for fluent, neutral speakers ready for global voice processes.\n\n![]()\n\nIcon\n\n### Sales\n\nAssess communication readiness for roles in sales and order support.\n\n![]()\n\nIcon\n\n### Banking and financial services\n\nHire customer-facing professionals who communicate with clarity and professionalism.\n\n![]()\n\nIcon\n\n### Healthcare and telemedicine\n\nEnsure effective spoken communication for remote consultations and patient interactions.\n\n![]()\n\nIcon\n\n### Hospitality and travel\n\nIdentify staff with strong spoken English for guest engagement and global clientele.\n\n![]()\n\n## Test anytime, anywhere without compromising on quality\n\nSpeechX powers communication assessments across diverse sectors\n\n!()\n\nWeb Mobile View\n\nDedicated mobile app equipped with proctoring capabilities.\n\nEnhanced recovery from internet disruptions.\n\nUninterrupted testing even when receiving calls.\n\nRestricted access to other apps during testing.\n\nBuilding relationships\n\n!()\n\nMasai success story\n\nSimplifying and scaling hiring for Masai School using our proctoring platform and talent assessments\n\n![]()\n\nquote-left\n\nSpeechX and the cheat-proof proctoring platform made our interview process efficacious. Mercer | Mettl helped save 15 minutes per interview per assessment, which saved us about 15,000 hours of effort per year. Mercer | Mettl also helped determine the accurate cut-off score for shortlisting candidates.\n\n\\- Yogesh Bhat\n\nCo-Founder and SVP, Holistic Development, Masai School\n\n![]()\n\nquote-left\n\n## Customer success stories\n\nHere’s how we helped our customers transform their strategies and build winning teams\n\n!()\n\nMasai success story\n\n!()\n\nMasai success story\n\n### About\n\nMasai is an outcome-driven career school that started in June 2019 to tap into the youth of India with the immense potential to be trained in the skills needed to be employable in the information technology (IT) job market.\n\nUse case: Applicant screening\n\n!()\n\nRight Arrow Icon\n\n### Business challenges\n\n* How to assess the English proficiency of potential applicants?\n \n* How to conduct credible exams and an ideal screening/interview process?\n \n\n### Solution\n\n* Enabled a customized SpeechX assessment to assess speaking ability in particular.\n \n* A remote proctoring platform with a secure browser where all tabs apart from the exam tab were disabled to minimize cheating.\n \n* Access to a test library comprising one lakh+ questions with advanced role-based simulators.\n \n\n### Impact\n\n* 101 to approximately 1 lakh (1000X) interviews conducted.\n \n* 15001 hours, equivalent to 8 years of effort and time, were saved after implementing SpeechX.\n \n* Accurate cut-off score shortened the screening time and helped shortlist the right candidates for the interview process.\n \n\n* * *\n\n## Frequently asked questions (FAQs)\n\nAn English language proficiency test is designed to evaluate how well a person can communicate in English across various dimensions—speaking, listening, reading, and writing. These English proficiency tests for employment assess vocabulary usage, grammatical accuracy, pronunciation, fluency, and comprehension to determine a candidate's command of the language. \nEnglish proficiency tests such as those powered by SpeechX are especially critical in roles that demand strong communication skills, including customer service, international sales, teaching, and global collaboration. The results align with global standards like CEFR, offering a reliable benchmark for decision-making.\n\nOrganizations can evaluate English speaking levels using digital assessment tools like SpeechX, which leverage AI and speech recognition to deliver consistent and unbiased results. These tools test four critical aspects of spoken English: pronunciation, fluency, grammar, and listening comprehension. By simulating real-life communication scenarios, they help employers assess how effectively a candidate can engage in conversations, follow instructions, and respond with clarity. Many platforms offer CEFR-aligned scoring and instant reports, making benchmarking communication skills against global standards easy. Such tools can be deployed at scale for remote or in-person hiring, workforce training, and skill gap identification, ensuring efficient talent screening and development.\n\nA voice and accent test (VNA) is an oral skills test to ascertain a prospect's fitment for client-facing roles. This test assesses language skills, such as English accent, speech clarity, pronunciation, intonation, listening skills, grammar, and fluency. This evaluation is typically conducted by a trained linguist, speech therapist, or language instructor. During the test, the individual is asked to speak and read aloud various words, phrases, and sentences in their target language, and their speech is closely observed and analyzed. \nThe purpose of a voice test for accent can vary widely, from assessing someone's language proficiency to helping them modify their pronunciation for improved communication and understanding in a new language or professional setting. Overall, accent tests are tests that aim to identify features of an individual's speech that may hinder effective communication or performance. Online English language tests serve as a valuable language proficiency test for language acquisition and skill enhancement.\n\nThe Common European Framework of Reference for Languages (CEFR) is a globally recognized framework that defines and measures language proficiency across six distinct levels - from beginner to advanced. Developed by the Council of Europe, it provides a common framework for educators, employers, and learners to assess language skills in reading, writing, listening, and speaking. \nThe CEFR framework allows organizations to set clear language benchmarks for different roles and training needs. Assessments aligned to CEFR offer standardized results, helping HR and L&D teams compare candidate performance across geographies and make consistent, data-driven decisions when hiring or training for communication-heavy roles. \nReports generated by SpeechX are aligned with CEFR standards, offering organizations a consistent and objective way to benchmark communication skills.\n\nThe CEFR framework is divided into six levels that indicate a learner’s language proficiency:\n\nA1 (Beginner) – Can understand and use basic expressions.\n\nA2 (Elementary) – Can communicate in simple and routine tasks.\n\nB1 (Intermediate) – Can handle most situations likely to arise during travel or work.\n\nB2 (Upper intermediate) – Can interact fluently and spontaneously.\n\nC1 (Advanced) – Can express ideas clearly in complex situations.\n\nC2 (Proficient) – Can communicate with native-level fluency and precision.\n\nSpeechX aligns its assessment results with these CEFR levels, helping organizations benchmark their employees’ spoken English proficiency for hiring decisions and personalized talent development plans.\n\nCarnegie Speech is a patented speech recognition technology developed by Carnegie Mellon University, a global leader in computer science and linguistics. It forms the core engine behind SpeechX, enabling the accurate assessment of pronunciation, fluency, grammar, and listening comprehension. Unlike generic speech tools, Carnegie Speech is designed to understand and evaluate non-native English speakers by accommodating diverse accents and speaking patterns. The technology uses advanced algorithms to simulate human-like evaluation, delivering fast, repeatable, and scalable results."}