{"rowid":"1607","url":"https://www.talentlyft.com/en/blog/article/94/what-is-recruitment-marketing-software","http":200,"status":"ok","method":"extractor","title":"What is Recruitment Marketing Software?","wordCount":1127,"text":"Recruitment Marketing\n\n# What is Recruitment Marketing Software?\n\n* Kristina Martic\n* February 2, 2018\n\nTable of contents\n\n## Recruitment Marketing Software: Exciting innovation or passing fad?\n\n## What is Recruitment Marketing?\n\n## What is Recruitment Marketing Software?\n\n## What are the benefits of Recruitment Marketing Software?\n\n### 1\\. Find candidates\n\n### 2\\. Attract candidates\n\n### 3\\. Engage and Nurture candidates\n\n### 4\\. Convert and Track candidates\n\n## Recruitment marketing software statistics\n\n## Who can use Recruitment Marketing Software?\n\n## Which Recruitment Marketing Software to buy?\n\nTable of contents\n\n## Recruitment Marketing Software: Exciting innovation or passing fad?\n\n## What is Recruitment Marketing?\n\n## What is Recruitment Marketing Software?\n\n## What are the benefits of Recruitment Marketing Software?\n\n### 1\\. Find candidates\n\n### 2\\. Attract candidates\n\n### 3\\. Engage and Nurture candidates\n\n### 4\\. Convert and Track candidates\n\n## Recruitment marketing software statistics\n\n## Who can use Recruitment Marketing Software?\n\n## Which Recruitment Marketing Software to buy?\n\nSee TalentLyft in action\n\nApplicant Tracking, Recruitment Marketing, Sourcing and Talent CRM software are powerful alone, but unstoppable when used together! \n\nRequest a demo\n\n**Recruitment Marketing Software** is a **software program** designed to help you **attract top talent** in the market. Since the current job market is candidate-driven, finding and hiring high-quality candidates has become no.1 HR problem. Recruitment Marketing Software offers a solution for this problem by applying **marketing methods** to recruitment process in order to find, attract, nurture and engage candidates and turn them into job applicants.\n\n## Recruitment Marketing Software: Exciting innovation or passing fad?\n\nThe way we recruit has changed.\n\nFinding and hiring ideal job candidates, especially those with in-demand skills, has become extremely hard, expensive and time-consuming.\n\nThe current job market is 90% candidate driven. That means you don’t pick talent anymore. **Talent picks you**.\n\nIn order to make yourself their employer of choice, you have to be able to attract them and trigger interest in them.\n\nThat’s where **Recruitment Marketing** comes in.\n\n## What is Recruitment Marketing?\n\n“ **Recruitment Marketing** ” is the term used for applying modern **marketing methods** and tactics **to the recruiting** process in order to attract top talent in the market.\n\nRecruitment Marketing is the process of **finding, attracting, engaging and nurturing** high-quality **candidates** using **marketing** **methods** and tactics.\n\nThe **main goal** of Recruitment Marketing is to drive talented individuals to **apply for the open positions** your company has available. This goal is achieved by developing **Employer Branding** strategies, showcasing **Employee Value Proposition** , encouraging **Candidate Engagement** and improving **Candidate Experience** .\n\nrecruitment-marketing\n\n## What is Recruitment Marketing Software?\n\n**Recruitment Marketing Software** is a type of HR software specialized for Recruitment Marketing.\n\n**Recruitment Marketing Software** is a software **program, tool or platform** designed to **automate, streamline and improve** Recruitment Marketing process and operations.\n\nIn other words, **Recruitment Marketing Software** helps companies **attract top talent** by applying **marketing methods** to the recruitment process.\n\nRecruitment Marketing Software is **also known as**:\n\n* Recruitment Marketing tool\n* Recruitment Marketing platform\n* Software application for Recruitment Marketing.\n\n## What are the benefits of Recruitment Marketing Software?\n\nRecruitment Marketing Software offers **solutions** for all the **5 stages** of Recruitment marketing process: **Finding, Attracting, Engaging, Nurturing** potential candidates and **Converting** them into applicants who apply for your open job positions.\n\n### 1\\. Find candidates\n\nRecruitment marketing platform includes solutions for:\n\n* **Web sourcing** of passive job seekers, your best job candidates\n* **One click job distribution** to multiple free and premium job boards\n* **Social Media** job promotion\n* Employee **Referral** Programs\n\n**Get our guide for finding high-quality job candidates!**\n\n### 2\\. Attract candidates\n\nRecruitment marketing platform offers features for:\n\n* Improving **Employer Branding**\n* **Social recruiting**\n* **Search Engine Optimization**\n* Creating branded **career site**\n\n### 3\\. Engage and Nurture candidates\n\nRecruitment marketing platform offers following features:\n\n* **Candidate Relationship Management**\n* **Email** recruiting **campaigns**\n* **Talent networking**\n* Career site team **blogging**\n\n### 4\\. Convert and Track candidates\n\nRecruitment marketing platform provides:\n\n* User-friendly **application form**\n* Hiring **Analytics**\n* **Reporting**\n\n**Get our checklist of most important hiring metrics you should be tracking!**\n\n## Recruitment marketing software statistics\n\nOkay, so now you're probably thinking:\n\n> All these benefits sounds great, but show me some numbers!\n\nNo problem!\n\nAccording to a research by the review site G2,\n\n* The estimated average ROI of recruitment marketing software is 9 months\n* 90% of customers using recruitment marketing software said they are likely to recommend it to other professionals.\n\n## Who can use Recruitment Marketing Software?\n\nSince Recruitment Marketing Software offers solutions for some of the biggest recruiting goals and challenges, it’s no wonder that the most of modern **recruiters** and **HR professionals** use these tools to advance their recruiting process and make their recruiting efforts more effective and successful.\n\nWith Recruitment Marketing Software, recruiters and HR professional can do all the recruitment related marketing by themselves. They don’t need an expert **marketing team** to support them, which cuts the costs of recruitment advertising drastically.\n\n**Small business owners** who don’t have a specialized HR department or a dedicated recruiter in their team can also reap huge benefits from investing in a recruiting software. Due to busy schedules and lack of time, many smaller businesses owners outsource their recruitment to agencies, which is quite expensive. But with these modern recruiting tools, small business owners can find and hire their ideal job candidates by easily managing their full cycle recruiting process and all related marketing operations.\n\n## Which Recruitment Marketing Software to buy?\n\n**Firstly, you should check out our checklist of most productive Recruitment Marketing strategies!**\n\nNow that we have presented all the solutions Recruitment Marketing Software can offer, let’s help you identify a type of a Recruitment Marketing Platform which would be **ideal for you**.\n\nSince Recruitment Marketing is a relatively new discipline, there is still not a lot of Recruitment Marketing Software out there. Make sure to check out our very own **TalentLyft Recruitment Marketing Platform** .\n\nOur **TalentLyft recruiting software** offers all in one, easy to use **Recruitment Marketing** and **Applicant Tracking System** tool to help you find, attract and hire best candidates.\n\nTalentLyft Source helps you **find** and reach best candidates, **TalentLyft Engage** makes it easy to **build relationships** with them and **TalentLyft Convert** encourages them to **apply**. Finally, **TalentLyft Track** offers the possibility to monitor your whole recruiting process in one place and provides invaluable **analysis, metrics and reports**.\n\nImprove your Recruitment Marketing efforts with TalentLyft\n\nTo see how TalentLyft has helped hundreds of companies improve their strategies, make sure to set up a consultation call!\n\nBook a quick call\n\n* Recruitment Software\n* Recruitment Marketing Strategy\n* Attracting Candidates\n\nSee TalentLyft in action\n\nApplicant Tracking, Recruitment Marketing, Sourcing and Talent CRM software are powerful alone, but unstoppable when used together! \n\nRequest a demo"}