{"rowid":"2215","url":"https://vervoe.com/psychometric-tests-vs-skills-assessments/","http":200,"status":"ok","method":"extractor","title":"Psychometric Tests vs Skills Assessments: Which Actually Predicts Job Performance?","wordCount":2192,"text":"Hiring Resources\n\n# Psychometric Tests vs Skills Assessments: Which Actually Predicts Job Performance?\n\nRaji Oluwaniyi\n\nBy Raji Oluwaniyi\n\ngroup-employees-working-office.jpg\n\nHiring the right candidate shouldn’t feel like a gamble, yet it often does. Many recruiters still rely on psychometric tests to reveal top candidates, driving a $72.9 million market1 in Australia alone. Yet, high scores don’t always translate to strong performance, and in today’s high-stakes hiring landscape, such guesswork is costly.\n\nRather than unreliable testing methods, organizations need tools that go beyond personality indicators and measure skills that truly matter. In this article, we’ll compare psychometric tests vs skills assessments, including the pitfalls of psychometric testing and how skills assessments offer more potent results.\n\n## What are psychometric tests?\n\nPsychometric tests are assessments designed to measure a candidate’s cognitive ability, behavioral style, and personality traits. They evaluate how a person thinks and responds to specific situations, thus revealing how they might behave in specific circumstances or act in social situations.\n\nSome common areas psychometric tests assess include numerical reasoning, verbal reasoning, extroversion, and emotional intelligence. In recruitment, these tests are typically used early in the hiring process to screen and compare candidates.\n\nFor example, an employer hiring for a finance role might use numerical reasoning tests to gauge analytical thinking. Similarly, a sales position might involve questions that assess social skills and persuasiveness.\n\n## The limits of psychometric tests\n\nimage-5.jpeg\n\n \n\nRecruiters use psychometric tests to check suitability for a role, but these tests do little to capture candidates’ abilities fully. As a result, many hire based on false data, leading to mishires. Below, we’ll discuss four of these limitations in detail.\n\n### 1\\. Weak correlation with job performance\n\nPsychometric tests measure candidates’ personality traits rather than their actual work outcomes and results. The problem with this approach is that a candidate’s behavior doesn’t necessarily predict their job fit.\n\nA good example is a customer service candidate scoring low on extroversion, which suggests limited social aptitude. However, in practice, they could excel through empathy, problem-solving, and active listening, qualities that personality tests can’t measure accurately.\n\nThis shows that relying too heavily on psychometric results risks screening out unconventional high performers who don’t fit a profile but still deliver exceptional performance.\n\n### 2\\. Risk of bias\n\nAlthough psychometric tests could appear bias-free, the reality is usually more complicated, as these tests rarely factor in candidate diversity. Unlike skills testing, which is strictly objective, personality tests can be affected by cultural differences or life experiences.\n\nWhen recruiters interpret test scores without considering these factors, they may unintentionally reinforce existing inequalities rather than eliminate them. Moreover, recruiters could subconsciously favor certain personality types over others, unfairly eliminating others because of biased preferences.\n\n### 3\\. Poor candidate experience\n\nPsychometric tests are generally unrelated to the jobs in question, which creates an impersonal and stressful experience for candidates. Lengthy or rigid assessments that feel irrelevant to the role make candidates disconnect from the hiring process, with some dropping out altogether.\n\nIn some cases, psychometric tests can be invasive or unethical and ask questions that candidates are uncomfortable responding to. For example, a personality test might probe into topics like religion, emotional trauma, or private lifestyle choices, details that can make candidates feel exposed or judged.\n\nThese experiences give them a negative impression of your brand, which could have lasting effects and dissuade great candidates from applying to future roles.\n\n### 4\\. Falsified or self-reported information\n\nRecruiters depend on accurate data from tests to make correct hiring decisions. However, psychometric tests are self-reported, which creates room for dishonesty or doctored profiles.\n\nCandidates know they’re being evaluated, so many adjust their answers to appear more agreeable, ambitious, or emotionally intelligent. This creates polished but unreliable profiles that tell recruiters what they want to hear rather than who the candidate really is.\n\nAs a result, the test’s integrity is compromised, making recruiters doubt their data and hire candidates who appear great but eventually fail to meet expectations.\n\n## What are skills assessments?\n\nSkills assessments are practical tests that measure a candidate’s ability to perform specific tasks or demonstrate knowledge directly relevant to the job. These tasks mirror the real challenges the role demands, allowing recruiters to see what candidates know and how they apply that knowledge in context.\n\nSkills assessments can evaluate both hard skills, such as coding or financial analysis, and soft skills like communication and leadership under realistic conditions. For example, a sales applicant might role-play a client pitch while a software engineering candidate could debug a piece of code.\n\nUnlike psychometric tests that attempt to infer potential through personality traits, skills assessments show how candidates actually think, solve problems, and deliver results. Many organizations also use them post-hire for onboarding or internal mobility to tailor training programs and identify high-performing employees for promotion.\n\n## How skills testing outperforms psychometric testing\n\nPsychometric tests leave recruiters guessing, but skills testing offers a more powerful alternative, showing you who can actually perform and thrive in the role. Here are a few practical ways skills assessment tests outperform psychometric testing:\n\n### 1\\. Strong predictive validity\n\nCompared to psychometric or personality tests, which could fail in their analysis of candidates’ abilities, skills testing consistently forecasts job performance accurately.\n\nBy evaluating how a candidate performs real or simulated work tasks, recruiters can directly observe problem-solving skills, attention to detail, and adaptability in tasks that replicate likely challenges on the job. This provides a clearer, more data-driven picture of future job success.\n\nFor example, a coding challenge will always reveal more about a software engineer’s readiness than a verbal or numerical reasoning test ever could. When hiring decisions are grounded in job-relevant performance data, the result is higher-quality hires and lower turnover rates.\n\n### 2\\. Direct measure of job fit\n\nWhile psychometric tests assess personality, skills assessments measure competence and are directly relevant to the job being done. Instead of inferring potential through abstract traits, they mirror the actual situations candidates will face in the role.\n\nThis alignment ensures you hire those whose skills and decision-making abilities genuinely match the job’s demands, rather than just vaguely smart or likeable people. It provides you with a clear, job-specific measure of job fit, balancing candidates’ theoretical knowledge with how they apply it practically.\n\n### 3\\. Reduced bias\n\nWhereas personality tests easily introduce bias into your hiring process, skills assessments judge candidates strictly by what they can do. Ability testing removes biased factors like background, race, or other demographics, letting you see candidates for their objective capabilities.\n\nThis levels the playing field for candidates with diverse educational, cultural, or socioeconomic experiences and lets candidates prove themselves to your hiring team. Without bias, you can guarantee a fairer, more inclusive recruitment process and stronger hiring results.\n\n### 4\\. Positive candidate experience\n\nCandidates in today’s hiring environment want an engaging, interactive test process, and skills assessments offer this advantage. Abstract personality tests are a turn-off for candidates, as most prefer having a chance to demonstrate their abilities, which skills tests allow them to do.\n\nCompleting realistic tasks also gives them a taste of the job itself, helping them decide whether it’s a good fit for them. This creates a more transparent and empowering hiring experience, boosting your assessment completion rates, offer acceptance, and overall reputation.\n\n### 5\\. Continuous employee development\n\nPersonality tests provide mostly static insights that do little to show the candidate’s weaknesses and areas for improvement in relation to the job. Meanwhile, skills tests generate actionable data that can be used beyond hiring for onboarding, upskilling, and internal mobility.\n\nUsing this data, you can identify skills gaps, track improvement over time, and design targeted training programs to strengthen your team. This transforms hiring from a one-time event into a continuous iterative process, helping you stay competitive and innovative as industry requirements evolve.\n\n### 6\\. Legal defensibility\n\nWhen a hiring decision is challenged by a candidate, a regulator, or your own leadership, the question is always the same: what was the basis for that decision?\n\nPsychometric assessments struggle to answer that question cleanly. Measuring personality traits and cognitive tendencies introduces variables that are difficult to validate against role performance, and in many jurisdictions, increasingly difficult to justify under equal employment and anti-discrimination frameworks.\n\nSkills-based assessment offers a fundamentally more defensible foundation. Every candidate is evaluated on the same role-specific tasks. Every response is scored against consistent, validated criteria. Every outcome is traceable and explainable — not as a compliance exercise, but as a natural consequence of how the assessment was designed.\n\n## The ROI of skills testing for organizations\n\nBeyond better hiring accuracy, skills testing delivers tangible business value, from faster results to improved employee satisfaction. The following are some benefits of skills-based hiring for your organization.\n\n### 1\\. Improved employee engagement and retention\n\nA Deloitte survey found that skills-based organizations are 98% more likely to retain high performers. Skills testing helps place new hires in positions where they can immediately contribute and see the impact of their abilities, a key driver of engagement.\n\nEmployees who feel capable and well-matched to their responsibilities are also more confident, productive, and satisfied, making them less likely to experience frustration or burnout. Such employees stay longer because they are motivated by their strong performance and require less daunting post-hire training, as they were a right fit from the start.\n\n### 2\\. Faster hiring cycles\n\nSkills assessment tests streamline recruitment by helping you identify qualified candidates earlier in the process. Rather than spending weeks sifting through resumes or scheduling multiple interviews, automated, role-specific tests quickly shortlist top performers based on objective results.\n\nThis speeds up decision-making and reduces the cost per hire without sacrificing quality. As a result, you can instantly see who meets your performance benchmarks, progress qualified candidates within days, and create a fast-paced pipeline regardless of application volume.\n\n### 3\\. Fairer talent pools and employee diversity\n\nBy eliminating bias, skills testing dramatically improves diversity and broadens access to talent, expanding Australian talent pools by up to 7.7x, according to LinkedIn. Its objective, task-based scoring evaluates candidates solely on performance, minimising the impact of unconscious bias and opening doors to diverse, non-traditional talent.\n\nThis helps you uncover candidates with fresh perspectives, facilitating innovation and preventing the tunnel vision that can come from having too similar employees. Over time, these assessments function as diversity and inclusion software, fostering genuine inclusivity due to merit-based evaluation and not a forced strategy.\n\n### 4\\. Scalable hiring strategy\n\nWhether you’re hiring for a small business, a high-volume organization, or growing your team, skills testing allows you to recruit without compromising quality. Automated skills assessments can be deployed globally, standardized across departments, and customized for different roles or levels of seniority.\n\nThis consistency ensures that every candidate, no matter where they apply, is evaluated using the same fair and relevant criteria. By replacing subjective screening methods with reliable data, you can make faster decisions at scale while building a workforce that continuously aligns with business goals.\n\n## Predict real job success with Vervoe’s skills assessments\n\nPsychometric tests fail to keep up with today’s hiring demands, miss real ability, and constantly overlook diverse talent. In modern hiring cycles, this leads to lost time, money, and credibility.\n\nVervoe is the skills intelligence platform built for enterprise hiring. Where others screen on background, Vervoe assesses on performance, putting candidates through role-specific tasks and real-world scenarios that reveal technical ability, behavioural skills and job readiness. Every response is automatically scored by AI against consistent, validated criteria giving hiring teams clear, comparable, and fully defensible evidence to act on. Faster decisions, stronger hires and a more capable organisation. \nSchedule a free demo with Vervoe and start hiring for real ability, not personality profiles.\n\n## References\n\nAustralia Psychometric Assessments Services Market By Type | Credence Research\n\nRaji Oluwaniyi\n\nRaji Oluwaniyi\n\nRaji Oluwaniyi is a seasoned Technical Content Writer at Vervoe with a rich background of over five years in the intersection of HR technology, consumer data protection, and SaaS. He has garnered significant recognition and has worked with industry stalwarts like TestGorilla, Brightlio, MakeUseOf, and Careerkarma. Oluwaniyi has a continuous drive to evolve and keep himself up to trend with the latest technology trends and best practices in writing. Beyond his professional pursuits, he is a genuine soccer fan and profoundly values his quality time with his close friends.\n\n## Similar articles you may be interested in\n\nupset-african-man-with-his-head-his-hands.jpg\n\nHiring Resources\n\n### How to Reduce Attrition Risk with Skills Validation and ARI\n\nEradicating attrition requires you to make changes early in your recruitment. Learn how to reduce attrition risk using ARI and skills testing in this guide.\n\nBy Shannon Rafferty·Mar 12, 2026\n\nfired-businessman-feeling-worried-about-loosing-his-job.jpg\n\nHiring Resources\n\n### How Weak Hiring Signals Turn Shortages into Attrition\n\nTalent shortages and turnover often stem from weak capability validation. Learn how missing skills signals at hiring drive mismatch, early exits, and repeated vacancies.\n\nBy Raji Oluwaniyi·Feb 19, 2026\n\nhappy-black-employee-excited-by-online-win-good-result.jpg\n\nHiring Resources\n\n### How to Balance AI and Human Judgment for Better Hiring Decisions\n\nIs AI replacing recruiters in modern hiring? Learn why combining AI hiring tools with human insight is important for stronger, balanced hiring below.\n\nBy Raji Oluwaniyi·Feb 15, 2026\n\nPublished March 12, 2026 · Updated March 12, 2026"}