{"rowid":"2235","url":"https://vervoe.com/5-different-ways-to-hire-software-engineers/","http":200,"status":"ok","method":"extractor","title":"5 Different Ways to Hire Software Engineers","wordCount":1388,"text":"Hiring Resources\n\n# 5 Different Ways to Hire Software Engineers\n\nEmily Heaslip\n\nBy Emily Heaslip\n\ntech-recruitment.jpg\n\nThe demand for coders, developers, and software engineers has skyrocketed over the last decade. Tech skills dominate LinkedIn’s 2019 list of most in-demand skills on employers’ wishlists. In the job market, 90% of developers have at least part-time work; 77% are employed full-time. There’s a very small number of developers who are unemployed and actively seeking employment – meaning the competition over these individuals is greater than ever.\n\nFor recruiters with no technical expertise in coding or programming, it can be challenging to assess whether the candidate you’re interviewing has the skills your company requires. But, with so few individuals on the market, it’s imperative to test a software engineer’s skills and assess their readiness. There’s no room for error: with so few candidates and such high demand, hiring teams must have a clear picture of a software engineer’s ability before they make a job offer.\n\nSkill testing can lead to better hires in virtually every position. Verifying a candidate’s ability, rather than making a hire based purely on what a resume says, leads to much higher on-the-job success. And, for software engineers, testing is relatively straightforward. Here are some of the different ways to test software engineers before making a job offer.\n\n## **Coding and programming tests**\n\nThere are over 200 different coding languages, but generally speaking, software engineers work in 12 main languages. A survey by Hackerrank found that in 2018, 73% of developers said they knew JavaScript, making it the year’s most well-known language. But, student developers aren’t learning JavaScript – it’s not taught in most university computer science programs.\n\nWhy is this discrepancy important? Many recruiters look at a candidate’s resume, see the computer science degree, and assume the candidate has the skills needed. Or, a recruiter dismisses an engineer’s self-taught JavaScript skills because they don’t come with the right pedigree or certification. Hiring teams could be missing out on great employees just because a candidate doesn’t get the chance to prove their skills.\n\nPre-recorded or one-way coding and programming tests can quickly ascertain whether or not a candidate has sufficient background in a coding language to take on the role’s responsibilities. These coding tests can be sent to a candidate to complete on their own time. Ask applicants to perform a coding challenge in which each individual solves simulated problems they may encounter while working for the company, such as finding a bug, writing in one language across different platforms, or synchronizing a multi-threaded application. Then, an AI tool can assess each candidate’s test and rank the candidates based on how well they performed – meaning the recruiter needs no technical background to see the results.\n\n## **Live coding challenges**\n\nSome companies ask their applicants to participate in live coding challenges. Applicants often dislike this pressurized simulation, but it can be very revealing for a recruiter.\n\nLive coding challenges differ from typical coding tests in that they happen in the presence of an interviewer, allowing the interviewer to observe in real-time how a candidate performs when faced with a problem for which they are unprepared. Usually, a recruiter can see how a candidate is thinking through their solution through screen sharing. The interviewer can see how a candidate approaches the problem from a technical perspective, as well as how they use their soft skills – logic, communication, patience – and how that person might fit with the rest of a team.\n\nCandidates find this experience stressful, but it is a good way to measure on-the-job success. As one expert points out, “At the end of the day, the aim of this exercise is not to produce (nor to evaluate) a perfectly constructed, perfectly neat piece of code. Indeed, live coding boils down to allowing both parties to gain an understanding of each other in a dynamic, conversational setting.”\n\n## **Coding questionnaires**\n\nIt may sound too easy to be true, but one of the best ways to test a software engineer is to...ask them questions?\n\n“Programming questionnaires can be a great way to quickly identify truly smart programmers. The biggest asset to these tests is that they are timely and evaluate not only a developer’s coding ability but also the way they problem-solve,” says one coding and development company.\n\nCoding questionnaires like FizzBuzz, Top Coder, and Google Code Jam seem deceptively easy at first. But, once you dig into the task, only the most experienced software engineers can achieve a high score on these questionnaires. On average, these tests should take no more than a few hours and can tell you a lot about a candidate’s abilities.\n\n## **Pair programming**\n\nLike a live coding challenge, pair programming allows a hiring team to see how the potential new hire will integrate with an existing team. Pair programming is when the candidate is paired with an experienced developer from the company to work together on a simulation for the afternoon. Have the recruiter or hiring manager play the role of “client” or “key stakeholder” within the organization. The recruiter presents the parameters of the exercise and briefs the pair on the simulation. Then, the candidate works with their partner to complete the challenge as if it’s a normal workday.\n\nThere are many obvious benefits to a pair programming challenge. It’s a quick way to evaluate a candidate’s hard and soft skills, from coding and time management to teamwork and communication. If you’re hiring for a customer-facing role, it’s also great to assess how the software engineer interacts with a mock client. And, you get the benefit of having an expert from your team assess the technical capabilities of the candidate, having coded next to them for a number of hours.\n\n## **Code reviews**\n\nAsk a candidate to perform a code review to verify their programming skills. A code review asks a programmer to look through a piece of code to find problems, errors, or bad practices. The main benefit of a code review is it test a different way of thinking; while some code tests have the candidate focus on the “what” – what the code needs to do – the code review focuses on the “how” – how does this piece of code work? A candidate can showcase a different level of understanding, which may be particularly important if you’re hiring for a strategic position.\n\nThere are plenty of ways to verify a software engineer’s skills. To learn how Vervoe can help you evaluate engineers, click here.\n\nEmily Heaslip\n\nEmily Heaslip\n\nEmily Heaslip is a wordsmith extraordinaire, weaving narratives that captivate and compel audiences across digital realms. With over eight years of experience in the art of storytelling, Emily has mastered the craft of freelance copywriting, infusing SEO strategies and content marketing tactics to craft captivating tales for brands such as HelloFresh, ADAY, and BlackRock. As the founder of Emily Heaslip Copywriting, Emily channels her creative energy into delivering unparalleled copywriting services that resonate with clients and audiences alike. Her journey from journalism to global relief efforts has imbued her writing with depth and authenticity, setting her apart as a versatile writer with a unique perspective. When she's not crafting captivating content, Emily can be found mentoring budding writers, sharing her wealth of knowledge and experience to empower the next generation of storytellers. With a passion for words and a talent for communication, Emily continues to inspire and connect through the power of storytelling.\n\n## Similar articles you may be interested in\n\ngroup-employees-working-office.jpg\n\nHiring Resources\n\n### Psychometric Tests vs Skills Assessments: Which Actually Predicts Job Performance?\n\nPersonality testing fails to predict job success. Learn why skills assessment tests are a faster, bias-free way to prove ability and hire top talent.\n\nBy Raji Oluwaniyi·Mar 12, 2026\n\nupset-african-man-with-his-head-his-hands.jpg\n\nHiring Resources\n\n### How to Reduce Attrition Risk with Skills Validation and ARI\n\nEradicating attrition requires you to make changes early in your recruitment. Learn how to reduce attrition risk using ARI and skills testing in this guide.\n\nBy Shannon Rafferty·Mar 12, 2026\n\nfired-businessman-feeling-worried-about-loosing-his-job.jpg\n\nHiring Resources\n\n### How Weak Hiring Signals Turn Shortages into Attrition\n\nTalent shortages and turnover often stem from weak capability validation. Learn how missing skills signals at hiring drive mismatch, early exits, and repeated vacancies.\n\nBy Raji Oluwaniyi·Feb 19, 2026\n\nPublished October 13, 2019 · Updated July 26, 2022"}